digfr/__init__.py
digfr/digfr.py
digfr-1.2.0.dist-info/METADATA
digfr-1.2.0.dist-info/WHEEL
digfr-1.2.0.dist-info/top_level.txt
digfr-1.2.0.dist-info/RECORD
